proxo/__init__.py
proxo/messages.py
proxo/protobuf.py
proxo-1.0.2.dist-info/DESCRIPTION.rst
proxo-1.0.2.dist-info/METADATA
proxo-1.0.2.dist-info/RECORD
proxo-1.0.2.dist-info/WHEEL
proxo-1.0.2.dist-info/metadata.json
proxo-1.0.2.dist-info/top_level.txt
