Metadata-Version: 2.0
Name: proxo
Version: 1.0.2
Summary: Object proxies (wrappers) for protobuf messages
Home-page: http://github.com/kszucs/proxo
Author: Krisztián Szűcs
Author-email: szucs.krisztian@gmail.com
License: Apache License, Version 2.0
Keywords: protobuf dict object wrapper proxy
Platform: UNKNOWN
Requires-Dist: protobuf
